{
    "AllRedeem": "N",
    "BuySell": "P",
    "BuySellType": "FRESH",
    "ClientCode": "manish1234",
    "DPC": "N",
    "DPTxn": "P",
    "EUIN": "E084436",
    "EUINVal": "Y",
    "FolioNo": null,
    "IPAdd": null,
    "KYCStatus": "Y",
    "MemberId": "PULSLAB1",
    "MinRedeem": "N",
    "OrderId": "1453378",
    "OrderVal": 10000.00,
    "Param1": null,
    "Param2": null,
    "Param3": null,
    "PassKey": "Pulselab",
    "Password": "E+EXGZtCuOi3bZFdhINts7W/XHYHmSo4esYz0vlRkdzTwxKQeWorQnXKjbYK9Kq5",
    "Qty": 0.00,
    "RefNo": null,
    "Remarks": null,
    "SchemeCd": "PSDP-DP",
    "SubBrCode": null,
    "TransCode": "NEW",
    "TransNo": "20190212",
    "UserID": "MANISH1"
}